singular_dbbackup_sender/__init__.py
singular_dbbackup_sender/database_backup.py
singular_dbbackup_sender-0.0.5.dist-info/METADATA
singular_dbbackup_sender-0.0.5.dist-info/WHEEL
singular_dbbackup_sender-0.0.5.dist-info/top_level.txt
singular_dbbackup_sender-0.0.5.dist-info/RECORD
