Metadata-Version: 2.1
Name: singular-dbbackup-sender
Version: 0.0.5
Summary: Server updater
Home-page: https://lucas@bitbucket.org/singular-dev/dbbackup_sender.git
Author: Singular Sistemas
Author-email: ivan@singular.inf.br
License: UNKNOWN
Platform: UNKNOWN
Requires-Python: >=3.6
Requires-Dist: django
Requires-Dist: django-crontab
Requires-Dist: django-dbbackup
